codeless_django/__init__.py
codeless_django/apps.py
codeless_django/data_manager.py
codeless_django/fields.json
codeless_django/tests.py
codeless_django/urls.py
codeless_django/views.py
codeless_django/additional_files/.gitignore
codeless_django/additional_files/root_urls.py
codeless_django/templates/codeless_django/base.html
codeless_django/templates/codeless_django/demo.html
codeless_django/templates/codeless_django/fields.html
codeless_django/templates/codeless_django/home.html
codeless_django/templates/codeless_django/forms/all_field_types.html
codeless_django/templates/codeless_django/forms/app_form.html
codeless_django/templates/codeless_django/forms/choice_option.html
codeless_django/templates/codeless_django/forms/common_option_form.html
codeless_django/templates/codeless_django/forms/dropdown_option.html
codeless_django/templates/codeless_django/forms/field_form.html
codeless_django/templates/codeless_django/forms/field_option.html
codeless_django/templates/codeless_django/forms/model_form.html
codeless_django/templates/codeless_django/forms/model_meta_form.html
codeless_django/templates/codeless_django/forms/option_form.html
codeless_django/templatetags/__init__.py
codeless_django/templatetags/codeless_django_tags.py
codeless_django/writers/__init__.py
codeless_django/writers/apis.py
codeless_django/writers/apps.py
codeless_django/writers/base.py
codeless_django/writers/documentation.py
codeless_django/writers/files.py
codeless_django/writers/models.py
codeless_django/writers/serializers.py
codeless_django/writers/views.py
codeless_django-0.0.11.dist-info/METADATA
codeless_django-0.0.11.dist-info/WHEEL
codeless_django-0.0.11.dist-info/licenses/LICENSE
codeless_django-0.0.11.dist-info/RECORD
