Metadata-Version: 2.1
Name: codeless-django
Version: 0.0.11
Summary: A Django app to create django apps, models, urls, views , api-views, documentation in a single click
Author-email: Omar Faruk <omar.iut.09@gmail.com>
License-File: LICENSE
Classifier: License :: OSI Approved :: BSD License
Classifier: Operating System :: OS Independent
Classifier: Programming Language :: Python :: 3
Requires-Python: >=3.7
